JenTrace/__init__.py
JenTrace/abr_fnc.py
JenTrace/catalog.py
JenTrace/mrt_fnc.py
JenTrace/opt_dsg.py
JenTrace/opt_sys.py
JenTrace/plt_fnc.py
JenTrace/ray_src.py
JenTrace/ray_trc.py
JenTrace/spt_dgm.py
JenTrace-1.0.3.dist-info/LICENSE
JenTrace-1.0.3.dist-info/METADATA
JenTrace-1.0.3.dist-info/WHEEL
JenTrace-1.0.3.dist-info/top_level.txt
JenTrace-1.0.3.dist-info/RECORD
