Metadata-Version: 2.1
Name: JenTrace
Version: 1.0.3
Summary: Python library for optical ray tracing
Home-page: https://github.com/dlvasquezp/JenTrace
Author: David L. Vasquez
Author-email: davidlvasquez@gmail.com
Project-URL: homepage, https://github.com/dlvasquezp/JenTrace
Project-URL: repository, https://github.com/dlvasquezp/JenTrace
Project-URL: documentation, https://github.com/dlvasquezp/JenTrace
Keywords: Ray tracing,Optical design,Software development,Optimization
Classifier: Programming Language :: Python
Requires-Python: >=3.7
License-File: LICENSE
